feray/__init__.py
feray/calculator.py
feray/py.typed
feray-1.0.0.dist-info/WHEEL
feray-1.0.0.dist-info/METADATA
feray-1.0.0.dist-info/RECORD
