Metadata-Version: 2.3
Name: feray
Version: 1.0.0
Summary: Memoization-enabled feature store on ray
Keywords: dagster,ray,feray,featurestore
Author: danielgafni, geoheil
Author-email: danielgafni <danielgafni16@gmail.com>, geoheil <georg.kf.heiler@gmail.com>
License: Apache-2.0
Classifier: Development Status :: 4 - Beta
Classifier: Intended Audience :: Developers
Classifier: License :: OSI Approved :: Apache Software License
Classifier: Operating System :: OS Independent
Classifier: Programming Language :: Python :: 3
Classifier: Programming Language :: Python :: 3.12
Classifier: Topic :: System :: Distributed Computing
Classifier: Topic :: Software Development :: Libraries :: Python Modules
Requires-Dist: ibis>=3.3.0
Requires-Dist: polars>=1.31.0
Requires-Dist: polars-hash>=0.5.4
Requires-Dist: sqlmodel>=0.0.24
Requires-Dist: ray>=2.48.0 ; extra == 'ray'
Requires-Python: >=3.12, <3.13
Project-URL: Bug Reports, https://github.com/feray-org/issues
Project-URL: Documentation, https://github.com/feray-org/docs/intro
Project-URL: Homepage, https://github.com/feray-org/
Project-URL: Repository, https://github.com/feray-org
Provides-Extra: ray
